{"pageProps":{"countryDataset":[{"date":"2020-1-22","confirmed":2,"deaths":0,"recovered":0,"countryName":"Japan","mortalityRate":0,"suffering":2},{"date":"2020-1-23","confirmed":2,"deaths":0,"recovered":0,"countryName":"Japan","mortalityRate":0,"suffering":2},{"date":"2020-1-24","confirmed":2,"deaths":0,"recovered":0,"countryName":"Japan","mortalityRate":0,"suffering":2},{"date":"2020-1-25","confirmed":2,"deaths":0,"recovered":0,"countryName":"Japan","mortalityRate":0,"suffering":2},{"date":"2020-1-26","confirmed":4,"deaths":0,"recovered":1,"countryName":"Japan","mortalityRate":0,"suffering":3},{"date":"2020-1-27","confirmed":4,"deaths":0,"recovered":1,"countryName":"Japan","mortalityRate":0,"suffering":3},{"date":"2020-1-28","confirmed":7,"deaths":0,"recovered":1,"countryName":"Japan","mortalityRate":0,"suffering":6},{"date":"2020-1-29","confirmed":7,"deaths":0,"recovered":1,"countryName":"Japan","mortalityRate":0,"suffering":6},{"date":"2020-1-30","confirmed":11,"deaths":0,"recovered":1,"countryName":"Japan","mortalityRate":0,"suffering":10},{"date":"2020-1-31","confirmed":15,"deaths":0,"recovered":1,"countryName":"Japan","mortalityRate":0,"suffering":14},{"date":"2020-2-1","confirmed":20,"deaths":0,"recovered":1,"countryName":"Japan","mortalityRate":0,"suffering":19},{"date":"2020-2-2","confirmed":20,"deaths":0,"recovered":1,"countryName":"Japan","mortalityRate":0,"suffering":19},{"date":"2020-2-3","confirmed":20,"deaths":0,"recovered":1,"countryName":"Japan","mortalityRate":0,"suffering":19},{"date":"2020-2-4","confirmed":22,"deaths":0,"recovered":1,"countryName":"Japan","mortalityRate":0,"suffering":21},{"date":"2020-2-5","confirmed":22,"deaths":0,"recovered":1,"countryName":"Japan","mortalityRate":0,"suffering":21},{"date":"2020-2-6","confirmed":22,"deaths":0,"recovered":1,"countryName":"Japan","mortalityRate":0,"suffering":21},{"date":"2020-2-7","confirmed":25,"deaths":0,"recovered":1,"countryName":"Japan","mortalityRate":0,"suffering":24},{"date":"2020-2-8","confirmed":25,"deaths":0,"recovered":1,"countryName":"Japan","mortalityRate":0,"suffering":24},{"date":"2020-2-9","confirmed":26,"deaths":0,"recovered":1,"countryName":"Japan","mortalityRate":0,"suffering":25},{"date":"2020-2-10","confirmed":26,"deaths":0,"recovered":4,"countryName":"Japan","mortalityRate":0,"suffering":22},{"date":"2020-2-11","confirmed":26,"deaths":0,"recovered":9,"countryName":"Japan","mortalityRate":0,"suffering":17},{"date":"2020-2-12","confirmed":28,"deaths":0,"recovered":9,"countryName":"Japan","mortalityRate":0,"suffering":19},{"date":"2020-2-13","confirmed":28,"deaths":1,"recovered":9,"countryName":"Japan","mortalityRate":0.03571428571428571,"suffering":18},{"date":"2020-2-14","confirmed":29,"deaths":1,"recovered":9,"countryName":"Japan","mortalityRate":0.034482758620689655,"suffering":19},{"date":"2020-2-15","confirmed":43,"deaths":1,"recovered":12,"countryName":"Japan","mortalityRate":0.023255813953488372,"suffering":30},{"date":"2020-2-16","confirmed":59,"deaths":1,"recovered":12,"countryName":"Japan","mortalityRate":0.01694915254237288,"suffering":46},{"date":"2020-2-17","confirmed":66,"deaths":1,"recovered":12,"countryName":"Japan","mortalityRate":0.015151515151515152,"suffering":53},{"date":"2020-2-18","confirmed":74,"deaths":1,"recovered":13,"countryName":"Japan","mortalityRate":0.013513513513513514,"suffering":60},{"date":"2020-2-19","confirmed":84,"deaths":1,"recovered":18,"countryName":"Japan","mortalityRate":0.011904761904761904,"suffering":65},{"date":"2020-2-20","confirmed":94,"deaths":1,"recovered":18,"countryName":"Japan","mortalityRate":0.010638297872340425,"suffering":75},{"date":"2020-2-21","confirmed":105,"deaths":1,"recovered":22,"countryName":"Japan","mortalityRate":0.009523809523809525,"suffering":82},{"date":"2020-2-22","confirmed":122,"deaths":1,"recovered":22,"countryName":"Japan","mortalityRate":0.00819672131147541,"suffering":99},{"date":"2020-2-23","confirmed":147,"deaths":1,"recovered":22,"countryName":"Japan","mortalityRate":0.006802721088435374,"suffering":124},{"date":"2020-2-24","confirmed":159,"deaths":1,"recovered":22,"countryName":"Japan","mortalityRate":0.006289308176100629,"suffering":136},{"date":"2020-2-25","confirmed":170,"deaths":1,"recovered":22,"countryName":"Japan","mortalityRate":0.0058823529411764705,"suffering":147},{"date":"2020-2-26","confirmed":189,"deaths":2,"recovered":22,"countryName":"Japan","mortalityRate":0.010582010582010581,"suffering":165},{"date":"2020-2-27","confirmed":214,"deaths":4,"recovered":22,"countryName":"Japan","mortalityRate":0.018691588785046728,"suffering":188},{"date":"2020-2-28","confirmed":228,"deaths":4,"recovered":22,"countryName":"Japan","mortalityRate":0.017543859649122806,"suffering":202},{"date":"2020-2-29","confirmed":241,"deaths":5,"recovered":32,"countryName":"Japan","mortalityRate":0.02074688796680498,"suffering":204},{"date":"2020-3-1","confirmed":256,"deaths":6,"recovered":32,"countryName":"Japan","mortalityRate":0.0234375,"suffering":218},{"date":"2020-3-2","confirmed":274,"deaths":6,"recovered":32,"countryName":"Japan","mortalityRate":0.021897810218978103,"suffering":236},{"date":"2020-3-3","confirmed":293,"deaths":6,"recovered":43,"countryName":"Japan","mortalityRate":0.020477815699658702,"suffering":244},{"date":"2020-3-4","confirmed":331,"deaths":6,"recovered":43,"countryName":"Japan","mortalityRate":0.01812688821752266,"suffering":282},{"date":"2020-3-5","confirmed":360,"deaths":6,"recovered":43,"countryName":"Japan","mortalityRate":0.016666666666666666,"suffering":311},{"date":"2020-3-6","confirmed":420,"deaths":6,"recovered":46,"countryName":"Japan","mortalityRate":0.014285714285714285,"suffering":368},{"date":"2020-3-7","confirmed":461,"deaths":6,"recovered":76,"countryName":"Japan","mortalityRate":0.013015184381778741,"suffering":379},{"date":"2020-3-8","confirmed":502,"deaths":6,"recovered":76,"countryName":"Japan","mortalityRate":0.01195219123505976,"suffering":420},{"date":"2020-3-9","confirmed":511,"deaths":10,"recovered":76,"countryName":"Japan","mortalityRate":0.019569471624266144,"suffering":425},{"date":"2020-3-10","confirmed":581,"deaths":10,"recovered":101,"countryName":"Japan","mortalityRate":0.01721170395869191,"suffering":470},{"date":"2020-3-11","confirmed":639,"deaths":15,"recovered":118,"countryName":"Japan","mortalityRate":0.023474178403755867,"suffering":506},{"date":"2020-3-12","confirmed":639,"deaths":16,"recovered":118,"countryName":"Japan","mortalityRate":0.025039123630672927,"suffering":505},{"date":"2020-3-13","confirmed":701,"deaths":19,"recovered":118,"countryName":"Japan","mortalityRate":0.02710413694721826,"suffering":564},{"date":"2020-3-14","confirmed":773,"deaths":22,"recovered":118,"countryName":"Japan","mortalityRate":0.028460543337645538,"suffering":633},{"date":"2020-3-15","confirmed":839,"deaths":22,"recovered":118,"countryName":"Japan","mortalityRate":0.026221692491060787,"suffering":699},{"date":"2020-3-16","confirmed":839,"deaths":27,"recovered":144,"countryName":"Japan","mortalityRate":0.03218116805721097,"suffering":668},{"date":"2020-3-17","confirmed":878,"deaths":29,"recovered":144,"countryName":"Japan","mortalityRate":0.03302961275626424,"suffering":705},{"date":"2020-3-18","confirmed":889,"deaths":29,"recovered":144,"countryName":"Japan","mortalityRate":0.03262092238470191,"suffering":716},{"date":"2020-3-19","confirmed":924,"deaths":29,"recovered":150,"countryName":"Japan","mortalityRate":0.031385281385281384,"suffering":745},{"date":"2020-3-20","confirmed":963,"deaths":33,"recovered":191,"countryName":"Japan","mortalityRate":0.03426791277258567,"suffering":739},{"date":"2020-3-21","confirmed":1007,"deaths":35,"recovered":232,"countryName":"Japan","mortalityRate":0.03475670307845084,"suffering":740},{"date":"2020-3-22","confirmed":1101,"deaths":41,"recovered":235,"countryName":"Japan","mortalityRate":0.03723887375113533,"suffering":825},{"date":"2020-3-23","confirmed":1128,"deaths":42,"recovered":235,"countryName":"Japan","mortalityRate":0.03723404255319149,"suffering":851},{"date":"2020-3-24","confirmed":1193,"deaths":43,"recovered":285,"countryName":"Japan","mortalityRate":0.03604358759430008,"suffering":865},{"date":"2020-3-25","confirmed":1307,"deaths":45,"recovered":310,"countryName":"Japan","mortalityRate":0.03442999234889059,"suffering":952},{"date":"2020-3-26","confirmed":1387,"deaths":47,"recovered":359,"countryName":"Japan","mortalityRate":0.033886085075702954,"suffering":981},{"date":"2020-3-27","confirmed":1468,"deaths":49,"recovered":372,"countryName":"Japan","mortalityRate":0.03337874659400545,"suffering":1047},{"date":"2020-3-28","confirmed":1693,"deaths":52,"recovered":404,"countryName":"Japan","mortalityRate":0.03071470761961016,"suffering":1237},{"date":"2020-3-29","confirmed":1866,"deaths":54,"recovered":424,"countryName":"Japan","mortalityRate":0.028938906752411574,"suffering":1388},{"date":"2020-3-30","confirmed":1866,"deaths":54,"recovered":424,"countryName":"Japan","mortalityRate":0.028938906752411574,"suffering":1388},{"date":"2020-3-31","confirmed":1953,"deaths":56,"recovered":424,"countryName":"Japan","mortalityRate":0.02867383512544803,"suffering":1473},{"date":"2020-4-1","confirmed":2178,"deaths":57,"recovered":472,"countryName":"Japan","mortalityRate":0.026170798898071626,"suffering":1649},{"date":"2020-4-2","confirmed":2495,"deaths":62,"recovered":472,"countryName":"Japan","mortalityRate":0.024849699398797595,"suffering":1961},{"date":"2020-4-3","confirmed":2617,"deaths":63,"recovered":514,"countryName":"Japan","mortalityRate":0.02407336645013374,"suffering":2040},{"date":"2020-4-4","confirmed":3139,"deaths":77,"recovered":514,"countryName":"Japan","mortalityRate":0.02453010512902198,"suffering":2548},{"date":"2020-4-5","confirmed":3139,"deaths":77,"recovered":514,"countryName":"Japan","mortalityRate":0.02453010512902198,"suffering":2548},{"date":"2020-4-6","confirmed":3654,"deaths":85,"recovered":575,"countryName":"Japan","mortalityRate":0.023262178434592228,"suffering":2994},{"date":"2020-4-7","confirmed":3906,"deaths":92,"recovered":592,"countryName":"Japan","mortalityRate":0.023553507424475168,"suffering":3222},{"date":"2020-4-8","confirmed":4257,"deaths":93,"recovered":622,"countryName":"Japan","mortalityRate":0.021846370683579985,"suffering":3542},{"date":"2020-4-9","confirmed":4667,"deaths":94,"recovered":632,"countryName":"Japan","mortalityRate":0.02014141847010928,"suffering":3941},{"date":"2020-4-10","confirmed":5530,"deaths":99,"recovered":685,"countryName":"Japan","mortalityRate":0.01790235081374322,"suffering":4746},{"date":"2020-4-11","confirmed":6005,"deaths":99,"recovered":762,"countryName":"Japan","mortalityRate":0.016486261448792672,"suffering":5144},{"date":"2020-4-12","confirmed":6748,"deaths":108,"recovered":762,"countryName":"Japan","mortalityRate":0.016004742145820983,"suffering":5878},{"date":"2020-4-13","confirmed":7370,"deaths":123,"recovered":784,"countryName":"Japan","mortalityRate":0.016689280868385347,"suffering":6463},{"date":"2020-4-14","confirmed":7645,"deaths":143,"recovered":799,"countryName":"Japan","mortalityRate":0.01870503597122302,"suffering":6703},{"date":"2020-4-15","confirmed":8100,"deaths":146,"recovered":853,"countryName":"Japan","mortalityRate":0.018024691358024692,"suffering":7101},{"date":"2020-4-16","confirmed":8626,"deaths":178,"recovered":901,"countryName":"Japan","mortalityRate":0.020635288662184094,"suffering":7547},{"date":"2020-4-17","confirmed":9787,"deaths":190,"recovered":935,"countryName":"Japan","mortalityRate":0.019413507714314906,"suffering":8662},{"date":"2020-4-18","confirmed":10296,"deaths":222,"recovered":1069,"countryName":"Japan","mortalityRate":0.02156177156177156,"suffering":9005},{"date":"2020-4-19","confirmed":10797,"deaths":236,"recovered":1159,"countryName":"Japan","mortalityRate":0.02185792349726776,"suffering":9402},{"date":"2020-4-20","confirmed":10797,"deaths":236,"recovered":1159,"countryName":"Japan","mortalityRate":0.02185792349726776,"suffering":9402},{"date":"2020-4-21","confirmed":11135,"deaths":263,"recovered":1239,"countryName":"Japan","mortalityRate":0.023619218679838346,"suffering":9633},{"date":"2020-4-22","confirmed":11512,"deaths":281,"recovered":1356,"countryName":"Japan","mortalityRate":0.024409312022237666,"suffering":9875},{"date":"2020-4-23","confirmed":12368,"deaths":328,"recovered":1494,"countryName":"Japan","mortalityRate":0.02652005174644243,"suffering":10546},{"date":"2020-4-24","confirmed":12829,"deaths":345,"recovered":1530,"countryName":"Japan","mortalityRate":0.026892197365344143,"suffering":10954},{"date":"2020-4-25","confirmed":13231,"deaths":360,"recovered":1656,"countryName":"Japan","mortalityRate":0.02720882775300431,"suffering":11215},{"date":"2020-4-26","confirmed":13441,"deaths":372,"recovered":1809,"countryName":"Japan","mortalityRate":0.02767651216427349,"suffering":11260},{"date":"2020-4-27","confirmed":14153,"deaths":385,"recovered":1899,"countryName":"Japan","mortalityRate":0.027202713205680774,"suffering":11869},{"date":"2020-4-28","confirmed":13736,"deaths":394,"recovered":1899,"countryName":"Japan","mortalityRate":0.028683750728013976,"suffering":11443},{"date":"2020-4-29","confirmed":13895,"deaths":413,"recovered":2368,"countryName":"Japan","mortalityRate":0.029722921914357683,"suffering":11114},{"date":"2020-4-30","confirmed":14088,"deaths":430,"recovered":2460,"countryName":"Japan","mortalityRate":0.03052243043725156,"suffering":11198},{"date":"2020-5-1","confirmed":14305,"deaths":455,"recovered":2975,"countryName":"Japan","mortalityRate":0.031807060468367704,"suffering":10875},{"date":"2020-5-2","confirmed":14571,"deaths":474,"recovered":3205,"countryName":"Japan","mortalityRate":0.03253036854025118,"suffering":10892},{"date":"2020-5-3","confirmed":14877,"deaths":487,"recovered":3981,"countryName":"Japan","mortalityRate":0.03273509444108355,"suffering":10409}]},"__N_SSG":true}