{"pageProps":{"countryDataset":[{"date":"2020-1-22","confirmed":0,"deaths":0,"recovered":0,"countryName":"Montenegro","mortalityRate":0,"suffering":0},{"date":"2020-1-23","confirmed":0,"deaths":0,"recovered":0,"countryName":"Montenegro","mortalityRate":0,"suffering":0},{"date":"2020-1-24","confirmed":0,"deaths":0,"recovered":0,"countryName":"Montenegro","mortalityRate":0,"suffering":0},{"date":"2020-1-25","confirmed":0,"deaths":0,"recovered":0,"countryName":"Montenegro","mortalityRate":0,"suffering":0},{"date":"2020-1-26","confirmed":0,"deaths":0,"recovered":0,"countryName":"Montenegro","mortalityRate":0,"suffering":0},{"date":"2020-1-27","confirmed":0,"deaths":0,"recovered":0,"countryName":"Montenegro","mortalityRate":0,"suffering":0},{"date":"2020-1-28","confirmed":0,"deaths":0,"recovered":0,"countryName":"Montenegro","mortalityRate":0,"suffering":0},{"date":"2020-1-29","confirmed":0,"deaths":0,"recovered":0,"countryName":"Montenegro","mortalityRate":0,"suffering":0},{"date":"2020-1-30","confirmed":0,"deaths":0,"recovered":0,"countryName":"Montenegro","mortalityRate":0,"suffering":0},{"date":"2020-1-31","confirmed":0,"deaths":0,"recovered":0,"countryName":"Montenegro","mortalityRate":0,"suffering":0},{"date":"2020-2-1","confirmed":0,"deaths":0,"recovered":0,"countryName":"Montenegro","mortalityRate":0,"suffering":0},{"date":"2020-2-2","confirmed":0,"deaths":0,"recovered":0,"countryName":"Montenegro","mortalityRate":0,"suffering":0},{"date":"2020-2-3","confirmed":0,"deaths":0,"recovered":0,"countryName":"Montenegro","mortalityRate":0,"suffering":0},{"date":"2020-2-4","confirmed":0,"deaths":0,"recovered":0,"countryName":"Montenegro","mortalityRate":0,"suffering":0},{"date":"2020-2-5","confirmed":0,"deaths":0,"recovered":0,"countryName":"Montenegro","mortalityRate":0,"suffering":0},{"date":"2020-2-6","confirmed":0,"deaths":0,"recovered":0,"countryName":"Montenegro","mortalityRate":0,"suffering":0},{"date":"2020-2-7","confirmed":0,"deaths":0,"recovered":0,"countryName":"Montenegro","mortalityRate":0,"suffering":0},{"date":"2020-2-8","confirmed":0,"deaths":0,"recovered":0,"countryName":"Montenegro","mortalityRate":0,"suffering":0},{"date":"2020-2-9","confirmed":0,"deaths":0,"recovered":0,"countryName":"Montenegro","mortalityRate":0,"suffering":0},{"date":"2020-2-10","confirmed":0,"deaths":0,"recovered":0,"countryName":"Montenegro","mortalityRate":0,"suffering":0},{"date":"2020-2-11","confirmed":0,"deaths":0,"recovered":0,"countryName":"Montenegro","mortalityRate":0,"suffering":0},{"date":"2020-2-12","confirmed":0,"deaths":0,"recovered":0,"countryName":"Montenegro","mortalityRate":0,"suffering":0},{"date":"2020-2-13","confirmed":0,"deaths":0,"recovered":0,"countryName":"Montenegro","mortalityRate":0,"suffering":0},{"date":"2020-2-14","confirmed":0,"deaths":0,"recovered":0,"countryName":"Montenegro","mortalityRate":0,"suffering":0},{"date":"2020-2-15","confirmed":0,"deaths":0,"recovered":0,"countryName":"Montenegro","mortalityRate":0,"suffering":0},{"date":"2020-2-16","confirmed":0,"deaths":0,"recovered":0,"countryName":"Montenegro","mortalityRate":0,"suffering":0},{"date":"2020-2-17","confirmed":0,"deaths":0,"recovered":0,"countryName":"Montenegro","mortalityRate":0,"suffering":0},{"date":"2020-2-18","confirmed":0,"deaths":0,"recovered":0,"countryName":"Montenegro","mortalityRate":0,"suffering":0},{"date":"2020-2-19","confirmed":0,"deaths":0,"recovered":0,"countryName":"Montenegro","mortalityRate":0,"suffering":0},{"date":"2020-2-20","confirmed":0,"deaths":0,"recovered":0,"countryName":"Montenegro","mortalityRate":0,"suffering":0},{"date":"2020-2-21","confirmed":0,"deaths":0,"recovered":0,"countryName":"Montenegro","mortalityRate":0,"suffering":0},{"date":"2020-2-22","confirmed":0,"deaths":0,"recovered":0,"countryName":"Montenegro","mortalityRate":0,"suffering":0},{"date":"2020-2-23","confirmed":0,"deaths":0,"recovered":0,"countryName":"Montenegro","mortalityRate":0,"suffering":0},{"date":"2020-2-24","confirmed":0,"deaths":0,"recovered":0,"countryName":"Montenegro","mortalityRate":0,"suffering":0},{"date":"2020-2-25","confirmed":0,"deaths":0,"recovered":0,"countryName":"Montenegro","mortalityRate":0,"suffering":0},{"date":"2020-2-26","confirmed":0,"deaths":0,"recovered":0,"countryName":"Montenegro","mortalityRate":0,"suffering":0},{"date":"2020-2-27","confirmed":0,"deaths":0,"recovered":0,"countryName":"Montenegro","mortalityRate":0,"suffering":0},{"date":"2020-2-28","confirmed":0,"deaths":0,"recovered":0,"countryName":"Montenegro","mortalityRate":0,"suffering":0},{"date":"2020-2-29","confirmed":0,"deaths":0,"recovered":0,"countryName":"Montenegro","mortalityRate":0,"suffering":0},{"date":"2020-3-1","confirmed":0,"deaths":0,"recovered":0,"countryName":"Montenegro","mortalityRate":0,"suffering":0},{"date":"2020-3-2","confirmed":0,"deaths":0,"recovered":0,"countryName":"Montenegro","mortalityRate":0,"suffering":0},{"date":"2020-3-3","confirmed":0,"deaths":0,"recovered":0,"countryName":"Montenegro","mortalityRate":0,"suffering":0},{"date":"2020-3-4","confirmed":0,"deaths":0,"recovered":0,"countryName":"Montenegro","mortalityRate":0,"suffering":0},{"date":"2020-3-5","confirmed":0,"deaths":0,"recovered":0,"countryName":"Montenegro","mortalityRate":0,"suffering":0},{"date":"2020-3-6","confirmed":0,"deaths":0,"recovered":0,"countryName":"Montenegro","mortalityRate":0,"suffering":0},{"date":"2020-3-7","confirmed":0,"deaths":0,"recovered":0,"countryName":"Montenegro","mortalityRate":0,"suffering":0},{"date":"2020-3-8","confirmed":0,"deaths":0,"recovered":0,"countryName":"Montenegro","mortalityRate":0,"suffering":0},{"date":"2020-3-9","confirmed":0,"deaths":0,"recovered":0,"countryName":"Montenegro","mortalityRate":0,"suffering":0},{"date":"2020-3-10","confirmed":0,"deaths":0,"recovered":0,"countryName":"Montenegro","mortalityRate":0,"suffering":0},{"date":"2020-3-11","confirmed":0,"deaths":0,"recovered":0,"countryName":"Montenegro","mortalityRate":0,"suffering":0},{"date":"2020-3-12","confirmed":0,"deaths":0,"recovered":0,"countryName":"Montenegro","mortalityRate":0,"suffering":0},{"date":"2020-3-13","confirmed":0,"deaths":0,"recovered":0,"countryName":"Montenegro","mortalityRate":0,"suffering":0},{"date":"2020-3-14","confirmed":0,"deaths":0,"recovered":0,"countryName":"Montenegro","mortalityRate":0,"suffering":0},{"date":"2020-3-15","confirmed":0,"deaths":0,"recovered":0,"countryName":"Montenegro","mortalityRate":0,"suffering":0},{"date":"2020-3-16","confirmed":0,"deaths":0,"recovered":0,"countryName":"Montenegro","mortalityRate":0,"suffering":0},{"date":"2020-3-17","confirmed":2,"deaths":0,"recovered":0,"countryName":"Montenegro","mortalityRate":0,"suffering":2},{"date":"2020-3-18","confirmed":2,"deaths":0,"recovered":0,"countryName":"Montenegro","mortalityRate":0,"suffering":2},{"date":"2020-3-19","confirmed":3,"deaths":0,"recovered":0,"countryName":"Montenegro","mortalityRate":0,"suffering":3},{"date":"2020-3-20","confirmed":14,"deaths":0,"recovered":0,"countryName":"Montenegro","mortalityRate":0,"suffering":14},{"date":"2020-3-21","confirmed":14,"deaths":0,"recovered":0,"countryName":"Montenegro","mortalityRate":0,"suffering":14},{"date":"2020-3-22","confirmed":21,"deaths":0,"recovered":0,"countryName":"Montenegro","mortalityRate":0,"suffering":21},{"date":"2020-3-23","confirmed":27,"deaths":1,"recovered":0,"countryName":"Montenegro","mortalityRate":0.037037037037037035,"suffering":26},{"date":"2020-3-24","confirmed":47,"deaths":1,"recovered":0,"countryName":"Montenegro","mortalityRate":0.02127659574468085,"suffering":46},{"date":"2020-3-25","confirmed":52,"deaths":1,"recovered":0,"countryName":"Montenegro","mortalityRate":0.019230769230769232,"suffering":51},{"date":"2020-3-26","confirmed":69,"deaths":1,"recovered":0,"countryName":"Montenegro","mortalityRate":0.014492753623188406,"suffering":68},{"date":"2020-3-27","confirmed":82,"deaths":1,"recovered":0,"countryName":"Montenegro","mortalityRate":0.012195121951219513,"suffering":81},{"date":"2020-3-28","confirmed":84,"deaths":1,"recovered":0,"countryName":"Montenegro","mortalityRate":0.011904761904761904,"suffering":83},{"date":"2020-3-29","confirmed":85,"deaths":1,"recovered":0,"countryName":"Montenegro","mortalityRate":0.011764705882352941,"suffering":84},{"date":"2020-3-30","confirmed":91,"deaths":1,"recovered":0,"countryName":"Montenegro","mortalityRate":0.01098901098901099,"suffering":90},{"date":"2020-3-31","confirmed":109,"deaths":2,"recovered":0,"countryName":"Montenegro","mortalityRate":0.01834862385321101,"suffering":107},{"date":"2020-4-1","confirmed":123,"deaths":2,"recovered":0,"countryName":"Montenegro","mortalityRate":0.016260162601626018,"suffering":121},{"date":"2020-4-2","confirmed":144,"deaths":2,"recovered":0,"countryName":"Montenegro","mortalityRate":0.013888888888888888,"suffering":142},{"date":"2020-4-3","confirmed":174,"deaths":2,"recovered":1,"countryName":"Montenegro","mortalityRate":0.011494252873563218,"suffering":171},{"date":"2020-4-4","confirmed":201,"deaths":2,"recovered":1,"countryName":"Montenegro","mortalityRate":0.009950248756218905,"suffering":198},{"date":"2020-4-5","confirmed":214,"deaths":2,"recovered":1,"countryName":"Montenegro","mortalityRate":0.009345794392523364,"suffering":211},{"date":"2020-4-6","confirmed":233,"deaths":2,"recovered":1,"countryName":"Montenegro","mortalityRate":0.008583690987124463,"suffering":230},{"date":"2020-4-7","confirmed":241,"deaths":2,"recovered":4,"countryName":"Montenegro","mortalityRate":0.008298755186721992,"suffering":235},{"date":"2020-4-8","confirmed":248,"deaths":2,"recovered":4,"countryName":"Montenegro","mortalityRate":0.008064516129032258,"suffering":242},{"date":"2020-4-9","confirmed":252,"deaths":2,"recovered":4,"countryName":"Montenegro","mortalityRate":0.007936507936507936,"suffering":246},{"date":"2020-4-10","confirmed":255,"deaths":2,"recovered":4,"countryName":"Montenegro","mortalityRate":0.00784313725490196,"suffering":249},{"date":"2020-4-11","confirmed":263,"deaths":2,"recovered":5,"countryName":"Montenegro","mortalityRate":0.0076045627376425855,"suffering":256},{"date":"2020-4-12","confirmed":272,"deaths":3,"recovered":5,"countryName":"Montenegro","mortalityRate":0.011029411764705883,"suffering":264},{"date":"2020-4-13","confirmed":274,"deaths":3,"recovered":5,"countryName":"Montenegro","mortalityRate":0.010948905109489052,"suffering":266},{"date":"2020-4-14","confirmed":283,"deaths":4,"recovered":46,"countryName":"Montenegro","mortalityRate":0.014134275618374558,"suffering":233},{"date":"2020-4-15","confirmed":288,"deaths":4,"recovered":55,"countryName":"Montenegro","mortalityRate":0.013888888888888888,"suffering":229},{"date":"2020-4-16","confirmed":303,"deaths":4,"recovered":55,"countryName":"Montenegro","mortalityRate":0.013201320132013201,"suffering":244},{"date":"2020-4-17","confirmed":303,"deaths":5,"recovered":55,"countryName":"Montenegro","mortalityRate":0.0165016501650165,"suffering":243},{"date":"2020-4-18","confirmed":307,"deaths":5,"recovered":55,"countryName":"Montenegro","mortalityRate":0.016286644951140065,"suffering":247},{"date":"2020-4-19","confirmed":308,"deaths":5,"recovered":55,"countryName":"Montenegro","mortalityRate":0.016233766233766232,"suffering":248},{"date":"2020-4-20","confirmed":312,"deaths":5,"recovered":88,"countryName":"Montenegro","mortalityRate":0.016025641025641024,"suffering":219},{"date":"2020-4-21","confirmed":313,"deaths":5,"recovered":101,"countryName":"Montenegro","mortalityRate":0.01597444089456869,"suffering":207},{"date":"2020-4-22","confirmed":315,"deaths":5,"recovered":116,"countryName":"Montenegro","mortalityRate":0.015873015873015872,"suffering":194},{"date":"2020-4-23","confirmed":316,"deaths":5,"recovered":123,"countryName":"Montenegro","mortalityRate":0.015822784810126583,"suffering":188},{"date":"2020-4-24","confirmed":319,"deaths":6,"recovered":123,"countryName":"Montenegro","mortalityRate":0.018808777429467086,"suffering":190},{"date":"2020-4-25","confirmed":320,"deaths":6,"recovered":153,"countryName":"Montenegro","mortalityRate":0.01875,"suffering":161},{"date":"2020-4-26","confirmed":321,"deaths":7,"recovered":153,"countryName":"Montenegro","mortalityRate":0.021806853582554516,"suffering":161},{"date":"2020-4-27","confirmed":321,"deaths":7,"recovered":189,"countryName":"Montenegro","mortalityRate":0.021806853582554516,"suffering":125},{"date":"2020-4-28","confirmed":321,"deaths":7,"recovered":199,"countryName":"Montenegro","mortalityRate":0.021806853582554516,"suffering":115},{"date":"2020-4-29","confirmed":322,"deaths":7,"recovered":203,"countryName":"Montenegro","mortalityRate":0.021739130434782608,"suffering":112},{"date":"2020-4-30","confirmed":322,"deaths":7,"recovered":214,"countryName":"Montenegro","mortalityRate":0.021739130434782608,"suffering":101},{"date":"2020-5-1","confirmed":322,"deaths":7,"recovered":233,"countryName":"Montenegro","mortalityRate":0.021739130434782608,"suffering":82},{"date":"2020-5-2","confirmed":322,"deaths":8,"recovered":245,"countryName":"Montenegro","mortalityRate":0.024844720496894408,"suffering":69},{"date":"2020-5-3","confirmed":322,"deaths":8,"recovered":249,"countryName":"Montenegro","mortalityRate":0.024844720496894408,"suffering":65}]},"__N_SSG":true}